bootstrapping/__init__.py
bootstrapping/bootstrapping.py
bootstrapping/cli.py
bootstrapping-0.1.2.dist-info/DESCRIPTION.rst
bootstrapping-0.1.2.dist-info/METADATA
bootstrapping-0.1.2.dist-info/RECORD
bootstrapping-0.1.2.dist-info/WHEEL
bootstrapping-0.1.2.dist-info/entry_points.txt
bootstrapping-0.1.2.dist-info/metadata.json
bootstrapping-0.1.2.dist-info/top_level.txt
