Metadata-Version: 2.0
Name: bootstrapping
Version: 0.1.2
Summary: Statistical Library for Bootstrapping
Home-page: https://github.com/knathanieltucker/bootstrapping
Author: K. Nathaniel Tucker
Author-email: k.nathaniel.tucker@gmail.com
License: MIT license
Keywords: bootstrapping
Platform: UNKNOWN
Classifier: Development Status :: 2 - Pre-Alpha
Classifier: Intended Audience :: Developers
Classifier: License :: OSI Approved :: MIT License
Classifier: Natural Language :: English
Classifier: Programming Language :: Python :: 2
Classifier: Programming Language :: Python :: 2.6
Classifier: Programming Language :: Python :: 2.7
Classifier: Programming Language :: Python :: 3
Classifier: Programming Language :: Python :: 3.3
Classifier: Programming Language :: Python :: 3.4
Classifier: Programming Language :: Python :: 3.5
Requires-Dist: Click (>=6.0)
